odoo10_addon_account_asset_management_import-10.0.1.0.0.99.dev2-py2.7-nspkg.pth
odoo/addons/account_asset_management_import/README.rst
odoo/addons/account_asset_management_import/__init__.py
odoo/addons/account_asset_management_import/__manifest__.py
odoo/addons/account_asset_management_import/i18n/account_asset_management_import.pot
odoo/addons/account_asset_management_import/static/description/icon.png
odoo/addons/account_asset_management_import/wizard/__init__.py
odoo/addons/account_asset_management_import/wizard/fixed_asset_import.py
odoo/addons/account_asset_management_import/wizard/fixed_asset_import.xml
odoo10_addon_account_asset_management_import-10.0.1.0.0.99.dev2.dist-info/METADATA
odoo10_addon_account_asset_management_import-10.0.1.0.0.99.dev2.dist-info/RECORD
odoo10_addon_account_asset_management_import-10.0.1.0.0.99.dev2.dist-info/WHEEL
odoo10_addon_account_asset_management_import-10.0.1.0.0.99.dev2.dist-info/namespace_packages.txt
odoo10_addon_account_asset_management_import-10.0.1.0.0.99.dev2.dist-info/top_level.txt
